py3commas/__init__.py
py3commas/config.py
py3commas/request.py
py3commas/test_request.py
py3commas-0.1.0.dist-info/LICENSE
py3commas-0.1.0.dist-info/METADATA
py3commas-0.1.0.dist-info/WHEEL
py3commas-0.1.0.dist-info/top_level.txt
py3commas-0.1.0.dist-info/RECORD
