Metadata-Version: 1.1
Name: py3commas
Version: 0.1.0
Summary: 3commas Python wrapper
Home-page: https://github.com/cichys/py3commas
Author: Stefano Cicatiello
Author-email: ste@anche.no
License: MIT
Keywords: api 3commas trading crypto bitcoin altcoin
Platform: UNKNOWN
Classifier: Development Status :: 4 - Beta
Classifier: Intended Audience :: Developers
Classifier: Topic :: Software Development :: Libraries
Classifier: Programming Language :: Python :: 2
Classifier: Programming Language :: Python :: 2.7
Classifier: Programming Language :: Python :: 3
Classifier: Programming Language :: Python :: 3.3
Classifier: Programming Language :: Python :: 3.4
Classifier: Programming Language :: Python :: 3.5
Classifier: Programming Language :: Python :: 3.6
Classifier: Programming Language :: Python :: Implementation :: PyPy
